[{"image": "page_2.png", "annotations": [{"label": "text", "coordinates": {"x": 293.0581395348837, "y": 144.67441860465112, "width": 325.0, "height": 77.0}}, {"label": "text", "coordinates": {"x": 870.5581395348837, "y": 276.1744186046511, "width": 1486.0, "height": 126.0}}, {"label": "text", "coordinates": {"x": 955.5581395348836, "y": 397.6744186046511, "width": 288.0, "height": 77.0}}, {"label": "text", "coordinates": {"x": 961.5581395348836, "y": 480.6744186046511, "width": 318.0, "height": 89.0}}, {"label": "text", "coordinates": {"x": 456.0581395348837, "y": 402.6744186046511, "width": 293.0, "height": 81.0}}, {"label": "text", "coordinates": {"x": 453.5581395348837, "y": 472.6744186046511, "width": 288.0, "height": 77.0}}, {"label": "img", "coordinates": {"x": 231.5581395348837, "y": 398.1744186046511, "width": 156.0, "height": 72.0}}, {"label": "img", "coordinates": {"x": 222.0581395348837, "y": 477.1744186046511, "width": 151.0, "height": 86.0}}, {"label": "img", "coordinates": {"x": 771.0581395348837, "y": 467.6744186046511, "width": 77.0, "height": 67.0}}, {"label": "img", "coordinates": {"x": 779.0581395348837, "y": 403.6744186046511, "width": 83.0, "height": 61.0}}, {"label": "img", "coordinates": {"x": 167.0581395348837, "y": 695.6744186046511, "width": 65.0, "height": 59.0}}, {"label": "img", "coordinates": {"x": 165.0581395348837, "y": 759.6744186046511, "width": 75.0, "height": 69.0}}, {"label": "img", "coordinates": {"x": 165.0581395348837, "y": 1008.674418604651, "width": 69.0, "height": 65.0}}, {"label": "img", "coordinates": {"x": 165.0581395348837, "y": 1061.174418604651, "width": 79.0, "height": 72.0}}, {"label": "img", "coordinates": {"x": 171.0581395348837, "y": 1307.174418604651, "width": 67.0, "height": 68.0}}, {"label": "img", "coordinates": {"x": 167.5581395348837, "y": 1370.174418604651, "width": 98.0, "height": 68.0}}, {"label": "img", "coordinates": {"x": 165.0581395348837, "y": 1685.174418604651, "width": 75.0, "height": 66.0}}, {"label": "img", "coordinates": {"x": 165.0581395348837, "y": 1750.674418604651, "width": 83.0, "height": 65.0}}, {"label": "img", "coordinates": {"x": 168.5581395348837, "y": 2003.674418604651, "width": 62.0, "height": 61.0}}, {"label": "text", "coordinates": {"x": 218.5581395348837, "y": 570.1744186046511, "width": 186.0, "height": 54.0}}, {"label": "text", "coordinates": {"x": 252.0581395348837, "y": 632.6744186046511, "width": 249.0, "height": 53.0}}, {"label": "text", "coordinates": {"x": 909.5581395348837, "y": 761.6744186046511, "width": 1400.0, "height": 191.0}}, {"label": "text", "coordinates": {"x": 686.0581395348836, "y": 1092.174418604651, "width": 967.0, "height": 232.0}}, {"label": "text", "coordinates": {"x": 896.5581395348837, "y": 1429.174418604651, "width": 1384.0, "height": 302.0}}, {"label": "text", "coordinates": {"x": 304.5581395348837, "y": 1620.174418604651, "width": 362.0, "height": 60.0}}, {"label": "text", "coordinates": {"x": 885.0581395348837, "y": 1744.674418604651, "width": 1365.0, "height": 179.0}}, {"label": "text", "coordinates": {"x": 231.5581395348837, "y": 1866.674418604651, "width": 174.0, "height": 65.0}}, {"label": "text", "coordinates": {"x": 237.0581395348837, "y": 1930.674418604651, "width": 247.0, "height": 49.0}}, {"label": "text", "coordinates": {"x": 861.5581395348837, "y": 2023.1744186046512, "width": 1304.0, "height": 128.0}}, {"label": "text", "coordinates": {"x": 1559.5581395348836, "y": 2095.6744186046512, "width": 30.0, "height": 49.0}}]}]