[{"image": "page_11.png", "annotations": [{"label": "text", "coordinates": {"x": 170.81443298969077, "y": 134.0, "width": 212.00000000000003, "height": 58.0}}, {"label": "text", "coordinates": {"x": 556.8144329896907, "y": 267.0, "width": 971.9999999999999, "height": 198.0}}, {"label": "text", "coordinates": {"x": 234.31443298969077, "y": 396.5, "width": 213.00000000000003, "height": 43.0}}, {"label": "text", "coordinates": {"x": 487.8144329896908, "y": 441.5, "width": 840.0, "height": 47.0}}, {"label": "text", "coordinates": {"x": 255.31443298969077, "y": 507.0, "width": 251.00000000000003, "height": 40.0}}, {"label": "text", "coordinates": {"x": 574.3144329896907, "y": 1031.5, "width": 1020.9999999999999, "height": 995.0}}]}]