[{"image": "page_17.png", "annotations": [{"label": "text", "coordinates": {"x": 526.8245614035089, "y": 313.421052631579, "width": 390.0, "height": 156.0}}, {"label": "text", "coordinates": {"x": 885.8245614035089, "y": 336.421052631579, "width": 244.0, "height": 114.0}}, {"label": "img", "coordinates": {"x": 588.324561403509, "y": 944.421052631579, "width": 975.0, "height": 1038.0}}, {"label": "text", "coordinates": {"x": 1009.824561403509, "y": 1555.421052631579, "width": 98.0, "height": 104.0}}]}]