[{"image": "page_4.png", "annotations": [{"label": "text", "coordinates": {"x": 262.5588235294118, "y": 127.88235294117663, "width": 284.0, "height": 62.000000000000014}}, {"label": "text", "coordinates": {"x": 263.0588235294118, "y": 252.38235294117663, "width": 279.0, "height": 65.0}}, {"label": "text", "coordinates": {"x": 628.5588235294117, "y": 343.88235294117663, "width": 997.9999999999999, "height": 68.0}}, {"label": "text", "coordinates": {"x": 464.0588235294118, "y": 407.88235294117663, "width": 643.0, "height": 54.0}}, {"label": "table", "coordinates": {"x": 841.5588235294118, "y": 971.8823529411766, "width": 1378.0, "height": 1080.0}}, {"label": "text", "coordinates": {"x": 334.5588235294118, "y": 1557.8823529411766, "width": 422.0, "height": 54.0}}, {"label": "text", "coordinates": {"x": 946.0588235294118, "y": 1702.8823529411766, "width": 1151.0, "height": 168.0}}, {"label": "text", "coordinates": {"x": 433.5588235294118, "y": 1863.3823529411766, "width": 674.0, "height": 63.0}}, {"label": "text", "coordinates": {"x": 810.0588235294118, "y": 1966.8823529411766, "width": 1423.0, "height": 128.0}}, {"label": "text", "coordinates": {"x": 1338.0588235294117, "y": 2225.3823529411766, "width": 223.0, "height": 75.0}}, {"label": "img", "coordinates": {"x": 252.55882352941182, "y": 1714.3823529411766, "width": 132.0, "height": 147.0}}]}]